glovebox/__init__.py
glovebox/__main__.py
glovebox/_version.py
glovebox/adapters/__init__.py
glovebox/adapters/compilation_progress_middleware.py
glovebox/adapters/config_file_adapter.py
glovebox/adapters/docker_adapter.py
glovebox/adapters/file_adapter.py
glovebox/adapters/template_adapter.py
glovebox/adapters/usb_adapter.py
glovebox/cli/README.md
glovebox/cli/__init__.py
glovebox/cli/__main__.py
glovebox/cli/app.py
glovebox/cli/workspace_display_utils.py
glovebox/cli/commands/__init__.py
glovebox/cli/commands/cloud.py
glovebox/cli/commands/metrics.py
glovebox/cli/commands/moergo.py
glovebox/cli/commands/status.py
glovebox/cli/commands/cache/__init__.py
glovebox/cli/commands/cache/clear.py
glovebox/cli/commands/cache/debug.py
glovebox/cli/commands/cache/delete.py
glovebox/cli/commands/cache/keys.py
glovebox/cli/commands/cache/show.py
glovebox/cli/commands/cache/utils.py
glovebox/cli/commands/cache/workspace.py
glovebox/cli/commands/cache/workspace_processing.py
glovebox/cli/commands/config/__init__.py
glovebox/cli/commands/config/edit.py
glovebox/cli/commands/config/management.py
glovebox/cli/commands/config/updates.py
glovebox/cli/commands/firmware/__init__.py
glovebox/cli/commands/firmware/base.py
glovebox/cli/commands/firmware/compile.py
glovebox/cli/commands/firmware/devices.py
glovebox/cli/commands/firmware/flash.py
glovebox/cli/commands/firmware/helpers.py
glovebox/cli/commands/layout/__init__.py
glovebox/cli/commands/layout/base.py
glovebox/cli/commands/layout/comparison.py
glovebox/cli/commands/layout/composition.py
glovebox/cli/commands/layout/core.py
glovebox/cli/commands/layout/dependencies.py
glovebox/cli/commands/layout/edit.py
glovebox/cli/commands/layout/file_operations.py
glovebox/cli/commands/layout/formatters.py
glovebox/cli/commands/layout/parsing.py
glovebox/cli/commands/library/__init__.py
glovebox/cli/commands/library/copy.py
glovebox/cli/commands/library/export.py
glovebox/cli/commands/library/fetch.py
glovebox/cli/commands/library/info.py
zmk_glovebox-0.1.1.dist-info/METADATA
zmk_glovebox-0.1.1.dist-info/WHEEL
zmk_glovebox-0.1.1.dist-info/entry_points.txt
zmk_glovebox-0.1.1.dist-info/licenses/LICENSE
zmk_glovebox-0.1.1.dist-info/RECORD
