Metadata-Version: 2.4
Name: zmk-glovebox
Version: 0.1.1
Summary: Comprehensive tool for ZMK keyboard firmware management
License-File: LICENSE
Requires-Python: >=3.11
Requires-Dist: colorlog>=6.9.0
Requires-Dist: cryptography>=42.0.0
Requires-Dist: deepdiff>=8.5.0
Requires-Dist: diskcache>=5.6.3
Requires-Dist: httpx>=0.28.1
Requires-Dist: jinja2>=3.1.0
Requires-Dist: jsonpatch>=1.33
Requires-Dist: keyring>=25.6.0
Requires-Dist: lark>=1.2.2
Requires-Dist: psutil>=7.0.0
Requires-Dist: pydantic-settings>=2.9.1
Requires-Dist: pydantic>=2.11.0
Requires-Dist: pyudev>=0.24.0; sys_platform == 'linux'
Requires-Dist: pyyaml>=6.0
Requires-Dist: requests>=2.32.4
Requires-Dist: rich>=13.3.0
Requires-Dist: tomlkit>=0.13.3
Requires-Dist: typer>=0.16.0
Requires-Dist: types-psutil>=7.0.0.20250601
Requires-Dist: wmi; sys_platform == 'win32'
